magic_afm/__init__.py
magic_afm/_make_version.py
magic_afm/_util.py
magic_afm/_vendored_lstsq.py
magic_afm/_vendored_root.py
magic_afm/_version.py
magic_afm/async_tools.py
magic_afm/calculation.py
magic_afm/data_readers.py
magic_afm/cli/__init__.py
magic_afm/cli/__main__.py
magic_afm/cli/_impl.py
magic_afm/gui/__init__.py
magic_afm/gui/__main__.py
magic_afm/gui/_impl.py
magic_afm-1.0.0b2.dist-info/licenses/LICENSE
magic_afm-1.0.0b2.dist-info/METADATA
magic_afm-1.0.0b2.dist-info/WHEEL
magic_afm-1.0.0b2.dist-info/entry_points.txt
magic_afm-1.0.0b2.dist-info/top_level.txt
magic_afm-1.0.0b2.dist-info/RECORD
