Metadata-Version: 2.4
Name: magic-afm
Version: 1.0.0b2
Summary: Code to analyze and understand Magic Ratio AFM
Author-email: richardsheridan <richard.sheridan@gmail.com>
Project-URL: Homepage, https://github.com/richardsheridan/magic-afm
Requires-Python: >=3.11
License-File: LICENSE
Requires-Dist: attrs>=23.2.0
Requires-Dist: numpy>=1.21
Requires-Dist: soxr
Provides-Extra: build
Requires-Dist: pyinstaller; extra == "build"
Requires-Dist: build; extra == "build"
Requires-Dist: twine; extra == "build"
Provides-Extra: cli
Requires-Dist: imageio; extra == "cli"
Requires-Dist: click; extra == "cli"
Requires-Dist: cloup; extra == "cli"
Requires-Dist: psutil; extra == "cli"
Requires-Dist: tqdm>=4.56.0; extra == "cli"
Provides-Extra: gui
Requires-Dist: imageio; extra == "gui"
Requires-Dist: psutil; extra == "gui"
Requires-Dist: matplotlib>=3.8.0; extra == "gui"
Requires-Dist: trio>=0.20.0; extra == "gui"
Requires-Dist: trio-parallel>1.1.0; extra == "gui"
Requires-Dist: tqdm>=4.56.0; extra == "gui"
Provides-Extra: notebook
Requires-Dist: notebook>=7; extra == "notebook"
Requires-Dist: ipywidgets; extra == "notebook"
Requires-Dist: scipy; extra == "notebook"
Requires-Dist: tqdm>=4.56.0; extra == "notebook"
Requires-Dist: matplotlib>=3.8.0; extra == "notebook"
Provides-Extra: numba
Requires-Dist: numba>=0.54.0; extra == "numba"
Provides-Extra: h5py
Requires-Dist: h5py>=3; extra == "h5py"
Dynamic: license-file
